powercrud/__init__.py
powercrud/admin.py
powercrud/apps.py
powercrud/async_context.py
powercrud/async_dashboard.py
powercrud/async_hooks.py
powercrud/async_manager.py
powercrud/conf.py
powercrud/logging.py
powercrud/schedules.py
powercrud/tasks.py
powercrud/urls.py
powercrud/validators.py
powercrud/assets/manifest.json
powercrud/assets/django_assets/powercrud-C-CzDXCL.css
powercrud/assets/django_assets/powercrud-Cu22Sgxq.js
powercrud/management/__init__.py
powercrud/management/commands/__init__.py
powercrud/management/commands/pcrud_cleanup_async.py
powercrud/management/commands/pcrud_extract_tailwind_classes.py
powercrud/management/commands/pcrud_help.py
powercrud/management/commands/pcrud_mktemplate.py
powercrud/migrations/0001_initial.py
powercrud/migrations/0002_delete_bulktask.py
powercrud/migrations/__init__.py
powercrud/mixins/__init__.py
powercrud/mixins/async_mixin.py
powercrud/mixins/core_mixin.py
powercrud/mixins/filtering_mixin.py
powercrud/mixins/form_mixin.py
powercrud/mixins/htmx_mixin.py
powercrud/mixins/inline_editing_mixin.py
powercrud/mixins/paginate_mixin.py
powercrud/mixins/table_mixin.py
powercrud/mixins/url_mixin.py
powercrud/mixins/bulk_mixin/__init__.py
powercrud/mixins/bulk_mixin/metadata_mixin.py
powercrud/mixins/bulk_mixin/operation_mixin.py
powercrud/mixins/bulk_mixin/roles.py
powercrud/mixins/bulk_mixin/selection_mixin.py
powercrud/mixins/bulk_mixin/view_mixin.py
powercrud/templates/powercrud/daisyUI/base.html
powercrud/templates/powercrud/daisyUI/bulk_edit_form.html
powercrud/templates/powercrud/daisyUI/crispy_partials.html
powercrud/templates/powercrud/daisyUI/object_confirm_delete.html
powercrud/templates/powercrud/daisyUI/object_detail.html
powercrud/templates/powercrud/daisyUI/object_form.html
powercrud/templates/powercrud/daisyUI/object_list.html
powercrud/templates/powercrud/daisyUI/layout/inline_field.html
powercrud/templates/powercrud/daisyUI/partial/bulk_edit_errors.html
django_powercrud-0.4.10.dist-info/METADATA
django_powercrud-0.4.10.dist-info/WHEEL
django_powercrud-0.4.10.dist-info/licenses/LICENSE
django_powercrud-0.4.10.dist-info/RECORD
