Metadata-Version: 2.4
Name: django-powercrud
Version: 0.4.10
Summary: Advanced CRUD for perfectionists with deadlines. An opinionated Neapolitan extension, with sprinkles.
Author: doctor-cornelius
License-File: LICENSE
Requires-Python: >=3.12
Requires-Dist: django-htmx<2.0,>=1.26.0
Requires-Dist: django-template-partials<25.3,>=25.2
Requires-Dist: pydantic<3.0,>=2.12.4
Provides-Extra: dev
Requires-Dist: commitizen<5,>=4.9.1; extra == 'dev'
Requires-Dist: ipykernel<8,>=7.1.0; extra == 'dev'
Provides-Extra: docs
Requires-Dist: mkdocs-awesome-nav<4,>=3; extra == 'docs'
Requires-Dist: mkdocs-enumerate-headings-plugin<0.7,>=0.6.2; extra == 'docs'
Requires-Dist: mkdocs-material<10,>=9.6.23; extra == 'docs'
Requires-Dist: mkdocs-mermaid2-plugin<2,>=1.2.3; extra == 'docs'
Requires-Dist: mkdocs<2,>=1.6.1; extra == 'docs'
Provides-Extra: tests-core
Requires-Dist: coverage<8,>=7.11.3; extra == 'tests-core'
Requires-Dist: crispy-daisyui<1,>=0.8.0; extra == 'tests-core'
Requires-Dist: crispy-tailwind<2,>=1.0.3; extra == 'tests-core'
Requires-Dist: django-crispy-forms<3,>=2.5; extra == 'tests-core'
Requires-Dist: django-q2<2,>=1.8.0; extra == 'tests-core'
Requires-Dist: django-redis<7,>=6.0.0; extra == 'tests-core'
Requires-Dist: django-vite<4,>=3.1.0; extra == 'tests-core'
Requires-Dist: django<6,>=4.2.25; extra == 'tests-core'
Requires-Dist: faker<38,>=37.12.0; extra == 'tests-core'
Requires-Dist: neapolitan<26,>=25.1; extra == 'tests-core'
Requires-Dist: psycopg-binary<4,>=3.2.12; extra == 'tests-core'
Requires-Dist: psycopg<4,>=3.2.12; extra == 'tests-core'
Requires-Dist: pytest-cov<8,>=7.0.0; extra == 'tests-core'
Requires-Dist: pytest-django<5,>=4.11.1; extra == 'tests-core'
Requires-Dist: pytest-mock<4,>=3.15.1; extra == 'tests-core'
Requires-Dist: pytest<9,>=8.4.2; extra == 'tests-core'
Requires-Dist: validators<1,>=0.35.0; extra == 'tests-core'
Provides-Extra: tests-ui
Requires-Dist: playwright<2,>=1.55.0; extra == 'tests-ui'
Requires-Dist: pytest-playwright<1,>=0.7.1; extra == 'tests-ui'
